{"dependencies":[{"name":"/Users/Kai/docker/MontageClient/src/.postcssrc.js","includedInParent":true,"mtime":1528096013081},{"name":"_css_loader"}],"generated":{"css":"body {\n  background: #efefef;\n  min-height: 100vh;\n  margin: 0;\n  padding: 0;\n  font-size: calc(10px + 2vmin);\n  color: #444;\n}\n","js":"\n        var reloadCSS = require('_css_loader');\n        module.hot.dispose(reloadCSS);\n        module.hot.accept(reloadCSS);\n      "},"hash":"89b4e12e85eb0d592f95cf0169d61fc5","cacheData":{}}